[
  {
    "key": "ctrl+shift+i",
    "command": "editor.action.formatDocument",
    "when": "editorHasDocumentFormattingProvider && editorHasDocumentFormattingProvider && editorTextFocus && !editorReadonly"
  },
  {
    "key": "ctrl+alt+down",
    "command": "editor.action.copyLinesDownAction",
    "when": "editorTextFocus && !editorReadonly"
  },
  {
    "key": "shift+alt+down",
    "command": "-editor.action.copyLinesDownAction",
    "when": "editorTextFocus && !editorReadonly"
  },
  {
    "key": "ctrl+alt+up",
    "command": "editor.action.copyLinesUpAction",
    "when": "editorTextFocus && !editorReadonly"
  },
  {
    "key": "shift+alt+up",
    "command": "-editor.action.copyLinesUpAction",
    "when": "editorTextFocus && !editorReadonly"
  },
  {
    "key": "ctrl+shift+up",
    "command": "editor.action.insertCursorAbove",
    "when": "editorTextFocus"
  },
  {
    "key": "ctrl+alt+up",
    "command": "-editor.action.insertCursorAbove",
    "when": "editorTextFocus"
  },
  {
    "key": "ctrl+shift+down",
    "command": "editor.action.insertCursorBelow",
    "when": "editorTextFocus"
  },
  {
    "key": "ctrl+alt+down",
    "command": "-editor.action.insertCursorBelow",
    "when": "editorTextFocus"
  },
  {
    "key": "ctrl+'",
    "command": "workbench.action.terminal.toggleTerminal"
  },
  {
    "key": "ctrl+n", // "cmd+n" on mac
    "command": "extension.advancedNewFile"
  },
  {
    "key": "ctrl+;",
    "command": "editor.action.commentLine"
  }
]
